llama_index/py.typed
llama_index/vector_stores/sqlalchemy/__init__.py
llama_index/vector_stores/sqlalchemy/base.py
llama_index/vector_stores/sqlalchemy/utils.py
llama_index_vector_stores_sqlalchemy-0.5.0.dist-info/METADATA
llama_index_vector_stores_sqlalchemy-0.5.0.dist-info/WHEEL
llama_index_vector_stores_sqlalchemy-0.5.0.dist-info/RECORD
