Metadata-Version: 2.1
Name: llama-index-vector-stores-sqlalchemy
Version: 0.5.0
Summary: llama-index vector_stores sqlalchemy integration
License: MIT
Author: Logan Markewich
Author-email: logan@runllama.ai
Requires-Python: >=3.9,<4.0
Classifier: License :: OSI Approved :: MIT License
Classifier: Programming Language :: Python :: 3
Classifier: Programming Language :: Python :: 3.9
Classifier: Programming Language :: Python :: 3.10
Classifier: Programming Language :: Python :: 3.11
Classifier: Programming Language :: Python :: 3.12
Requires-Dist: llama-index-core (>=0.12.0,<0.13.0)
Requires-Dist: sqlalchemy (>=2.0)
